emission/EmissionJSONReader.py
emission/Extrapolate.py
emission/Interpolate.py
emission/Pollutants.py
emission/__init__.py
emission/__version__.py
emission/database.db
emission/exceptions.py
emission/models.py
emission/planner.py
emission/roadTransport.json.gz
emission/trucksEmissions.json.gz
emission/update_db.py
emission/vehicles.py
emission-0.3.6.dist-info/DESCRIPTION.rst
emission-0.3.6.dist-info/METADATA
emission-0.3.6.dist-info/RECORD
emission-0.3.6.dist-info/WHEEL
emission-0.3.6.dist-info/metadata.json
emission-0.3.6.dist-info/top_level.txt
