Metadata-Version: 2.0
Name: emission
Version: 0.3.6
Summary: Emission calculator library
Home-page: https://github.com/NPRA/EmissionCalculatorLib
Author: Juraj Cirbus <Juraj.Cirbus@norconsult.com>, Tomas Levin <tomas.levin@vegvesen.no>, Asbjørn Alexander Fellinghaug <asbjorn.fellinghaug@webstep.no>
Author-email: asbjorn@fellinghaug.com
License: BSD
Keywords: Emission calculation library using the NVDB (Norway)
Platform: UNKNOWN
Classifier: Development Status :: 4 - Beta
Classifier: License :: OSI Approved :: BSD License
Classifier: Programming Language :: Python
Classifier: Programming Language :: Python :: 2.7
Classifier: Programming Language :: Python :: 3
Classifier: Programming Language :: Python :: 3.3
Classifier: Programming Language :: Python :: 3.4
Classifier: Programming Language :: Python :: 3.5
Classifier: Programming Language :: Python :: 3.6
Classifier: Programming Language :: Python :: Implementation :: CPython
Classifier: Intended Audience :: Developers
Classifier: Intended Audience :: Education
Classifier: Intended Audience :: Science/Research
Classifier: Topic :: Education
Classifier: Topic :: Office/Business
Requires-Dist: numpy
Requires-Dist: SQLAlchemy
Requires-Dist: six
